secpar/__init__.py
secpar/__main__.py
secpar/lib/Commands/AbstractCommand.py
secpar/lib/Commands/CommandFactory.py
secpar/lib/Commands/InitCommand.py
secpar/lib/Commands/ScrapeCommand.py
secpar/lib/Commands/__pycache__/AbstractCommand.cpython-310.pyc
secpar/lib/Commands/__pycache__/CommandFactory.cpython-310.pyc
secpar/lib/Commands/__pycache__/InitCommand.cpython-310.pyc
secpar/lib/Commands/__pycache__/ScrapeCommand.cpython-310.pyc
secpar/lib/Formatters/AbstractFormatter.py
secpar/lib/Formatters/CodeforcesFormatter.py
secpar/lib/Formatters/CsesFormatter.py
secpar/lib/Formatters/ReadMeBuilder.py
secpar/lib/Formatters/VjudgeFormatter.py
secpar/lib/Formatters/__pycache__/AbstractFormatter.cpython-310.pyc
secpar/lib/Formatters/__pycache__/CodeforcesFormatter.cpython-310.pyc
secpar/lib/Formatters/__pycache__/CsesFormatter.cpython-310.pyc
secpar/lib/Formatters/__pycache__/ReadMeBuilder.cpython-310.pyc
secpar/lib/Formatters/__pycache__/VjudgeFormatter.cpython-310.pyc
secpar/lib/Input/args.py
secpar/lib/Input/__pycache__/args.cpython-310.pyc
secpar/lib/Resources/Extensions/CodeforcesExtensions.json
secpar/lib/Resources/Extensions/CsesExtensions.json
secpar/lib/Resources/Extensions/VjudgeExtensions.json
secpar/lib/Resources/User/UserData.json
secpar/lib/Resources/User/x.json
secpar/lib/Scrapers/AbstractScraper.py
secpar/lib/Scrapers/CodeforcesScraper.py
secpar/lib/Scrapers/CsesScraper.py
secpar/lib/Scrapers/ScraperFactory.py
secpar/lib/Scrapers/VjudgeScraper.py
secpar/lib/Scrapers/__pycache__/AbstractScraper.cpython-310.pyc
secpar/lib/Scrapers/__pycache__/CodeforcesScraper.cpython-310.pyc
secpar/lib/Scrapers/__pycache__/CsesScraper.cpython-310.pyc
secpar/lib/Scrapers/__pycache__/ScraperFactory.cpython-310.pyc
secpar/lib/Scrapers/__pycache__/VjudgeScraper.cpython-310.pyc
Secpar-1.1.4.dist-info/LICENSE
Secpar-1.1.4.dist-info/METADATA
Secpar-1.1.4.dist-info/WHEEL
Secpar-1.1.4.dist-info/entry_points.txt
Secpar-1.1.4.dist-info/top_level.txt
Secpar-1.1.4.dist-info/RECORD
