Metadata-Version: 2.1
Name: Secpar
Version: 1.1.4
Summary: Scrape problems submissions from different platforms
Home-page: https://github.com/MostafaGalal1/Secpar
Author: Mostafa Galal <mostafam.galal82@gmail.com>, Mahmoud Goda <mahmoden17@gmail.com>
License: MIT
Keywords: CP,scraper,secpar,problem solving,python,tools
Classifier: Development Status :: 5 - Production/Stable
Classifier: Intended Audience :: End Users/Desktop
Classifier: License :: OSI Approved :: MIT License
Classifier: Programming Language :: Python :: 3
Classifier: Operating System :: OS Independent
Requires-Python: >=3.5
License-File: LICENSE
Requires-Dist: PyGithub >=1.54.0
Requires-Dist: requests >=2.0.0
Requires-Dist: beautifulsoup4 >=4.0.0
Requires-Dist: stem >=1.8.0
Requires-Dist: PySocks <2.0.0,>=1.7.1
Requires-Dist: argparse >=1.4.0
